agentgym/__init__.py
agentgym/main.py
agentgym/majority_voting.py
agentgym/r1_pipeline.py
agentgym/reward_funcs.py
agentgym-0.0.2.dist-info/LICENSE
agentgym-0.0.2.dist-info/METADATA
agentgym-0.0.2.dist-info/WHEEL
agentgym-0.0.2.dist-info/RECORD
